wagtail_graphql/__init__.py
wagtail_graphql/apps.py
wagtail_graphql/checks.py
wagtail_graphql/converters.py
wagtail_graphql/models.py
wagtail_graphql/schema.py
wagtail_graphql/settings.py
wagtail_graphql/utils.py
wagtail_graphql/inventory/__init__.py
wagtail_graphql/inventory/base.py
wagtail_graphql/inventory/models.py
wagtail_graphql/inventory/pages.py
wagtail_graphql/inventory/snippets.py
wagtail_graphql/query_mixins/__init__.py
wagtail_graphql/query_mixins/base.py
wagtail_graphql/query_mixins/documents.py
wagtail_graphql/query_mixins/images.py
wagtail_graphql/query_mixins/pages.py
wagtail_graphql/query_mixins/sites.py
wagtail_graphql/query_mixins/snippets.py
wagtail_graphql/tests/__init__.py
wagtail_graphql/tests/settings.py
wagtail_graphql/tests/test_pages.py
wagtail_graphql/tests/urls.py
wagtail_graphql/tests/home/__init__.py
wagtail_graphql/tests/home/models.py
wagtail_graphql/tests/home/migrations/0001_initial.py
wagtail_graphql/tests/home/migrations/0002_create_homepage.py
wagtail_graphql/tests/home/migrations/__init__.py
wagtail_graphql/types/__init__.py
wagtail_graphql/types/base.py
wagtail_graphql/types/collection.py
wagtail_graphql/types/documents.py
wagtail_graphql/types/images.py
wagtail_graphql/types/pages.py
wagtail_graphql/types/scalars.py
wagtail_graphql/types/site.py
wagtail_graphql/types/snippets.py
wagtail_graphql/types/streamfields.py
wagtail_graphql/types/structures.py
wagtail_graphql_api-0.0.1a0.dist-info/LICENSE
wagtail_graphql_api-0.0.1a0.dist-info/WHEEL
wagtail_graphql_api-0.0.1a0.dist-info/METADATA
wagtail_graphql_api-0.0.1a0.dist-info/RECORD
